README.md
keras_util.py
setup.py
keras_util.egg-info/PKG-INFO
keras_util.egg-info/SOURCES.txt
keras_util.egg-info/dependency_links.txt
keras_util.egg-info/requires.txt
keras_util.egg-info/top_level.txt