Metadata-Version: 2.1
Name: keras-util
Version: 0.0.2
Summary: plots training hystory of Keras model
Home-page: https://github.com/smile-on/keras_util
Author: Slav Kochepasov
License: UNKNOWN
Keywords: keras util plot history
Platform: UNKNOWN
Requires-Python: >=3
